knx_plugin/__init__.py
knx_plugin/message.py
knx_plugin/client/__init__.py
knx_plugin/client/knxnet_ip.py
knx_plugin/client/usbhid.py
knx_plugin/command/__init__.py
knx_plugin/command/custom_clima.py
knx_plugin/command/dpt_brightness.py
knx_plugin/command/dpt_switch.py
knx_plugin/command/dpt_updown.py
knx_plugin/gateway/__init__.py
knx_plugin/gateway/knxnet_ip.py
knx_plugin/gateway/usbhid.py
knx_plugin/tests/__init__.py
knx_plugin/tests/test_courtesy.py
knx_plugin/tests/test_curtain_stop.py
knx_plugin/tests/test_doctests.py
knx_plugin/tests/test_gateway.py
knx_plugin/tests/test_multiple_protocol_triggers.py
knx_plugin/tests/test_performer_brightness_update.py
knx_plugin/tests/test_performer_power_update.py
knx_plugin/tests/test_performer_switch_update.py
knx_plugin/tests/test_performer_temperature_update.py
knx_plugin/tests/test_performer_thermostat.py
knx_plugin/tests/test_postpone_switchoff.py
knx_plugin/tests/test_presence.py
knx_plugin/tests/test_scene_timer.py
knx_plugin/tests/test_windy.py
knx_plugin/tests/testcase.py
knx_plugin/trigger/__init__.py
knx_plugin/trigger/custom_clima.py
knx_plugin/trigger/custom_scene.py
knx_plugin/trigger/dpt_brightness.py
knx_plugin/trigger/dpt_scene_control.py
knx_plugin/trigger/dpt_start.py
knx_plugin/trigger/dpt_switch.py
knx_plugin/trigger/dpt_updown.py
knx_plugin/trigger/dpt_value_temp.py
knx_plugin/trigger/dpt_value_wsp.py
knx_plugin/trigger/dpt_control_dimming/__init__.py
knx_plugin/trigger/dpt_control_dimming/step/__init__.py
knx_plugin/trigger/dpt_control_dimming/step/down.py
knx_plugin/trigger/dpt_control_dimming/step/up.py
knx_plugin/trigger/dpt_value_lux/__init__.py
knx_plugin/trigger/dpt_value_lux/balance.py
knx_plugin/trigger/dpt_value_power/__init__.py
knx_plugin/trigger/dpt_value_power/consumption.py
knx_plugin/trigger/dpt_value_power/production.py
knx_plugin/trigger/mean/__init__.py
automate_knx_plugin-0.9.1.dist-info/LICENSE
automate_knx_plugin-0.9.1.dist-info/METADATA
automate_knx_plugin-0.9.1.dist-info/WHEEL
automate_knx_plugin-0.9.1.dist-info/top_level.txt
automate_knx_plugin-0.9.1.dist-info/RECORD
