Metadata-Version: 2.1
Name: automate-knx-plugin
Version: 0.9.1
Summary: A KNX plugin for automate-home
Home-page: https://github.com/majamassarini/automate-home
Author: Maja Massarini
Author-email: maja.massarini@gmail.com
License: MIT
Platform: UNKNOWN
Classifier: Development Status :: 3 - Alpha
Classifier: License :: OSI Approved :: MIT License
Classifier: Operating System :: POSIX :: Linux
Classifier: Programming Language :: Python :: 3.8
Classifier: Topic :: Communications
Classifier: Intended Audience :: Developers
License-File: LICENSE
Requires-Dist: automate-home
Requires-Dist: knx-stack
